AUTHORS
CHANGES
INSTALL
LICENSE
MANIFEST.in
README.md
setup.py
cmsplugin_configurableproduct/__init__.py
cmsplugin_configurableproduct/cms_plugins.py
cmsplugin_configurableproduct/forms.py
cmsplugin_configurableproduct/models.py
cmsplugin_configurableproduct.egg-info/PKG-INFO
cmsplugin_configurableproduct.egg-info/SOURCES.txt
cmsplugin_configurableproduct.egg-info/dependency_links.txt
cmsplugin_configurableproduct.egg-info/requires.txt
cmsplugin_configurableproduct.egg-info/top_level.txt
cmsplugin_configurableproduct/lib/__init__.py
cmsplugin_configurableproduct/lib/choices.py
cmsplugin_configurableproduct/lib/formatting.py
cmsplugin_configurableproduct/migrations/0001_initial.py
cmsplugin_configurableproduct/migrations/__init__.py
cmsplugin_configurableproduct/templates/cmsplugin_configurableproduct/base.html
cmsplugin_configurableproduct/templates/cmsplugin_configurableproduct/product-list/default.html
cmsplugin_configurableproduct/templates/cmsplugin_configurableproduct/product-types/default.html
cmsplugin_configurableproduct/templates/cmsplugin_configurableproduct/snippets/product-display-only.html