Metadata-Version: 1.0
Name: cmsplugin-configurableproduct
Version: 0.0.11
Summary: DjangoCMS plugin for django-shop-configurableproduct
Home-page: http://github.com/airtonix/cmsplugin-configurableproduct
Author: Zenobius Jiricek
Author-email: airtonix@gmail.com
License: BSD
Keywords: django-cms,plugin,django-shop,product
Platform: UNKNOWN
Classifier: Development Status :: 4 - Beta
Classifier: Framework :: Django
Classifier: Intended Audience :: Developers
Classifier: License :: OSI Approved :: BSD License
Classifier: Operating System :: OS Independent
Classifier: Programming Language :: Python
Classifier: Topic :: Internet :: WWW/HTTP
